gbeampro/.gitattributes
gbeampro/.gitignore
gbeampro/README.md
gbeampro/__init__.py
gbeampro/beambase.py
gbeampro/helper.py
gbeampro/examples/beam_focusing_into_crystal.ipynb
gbeampro/examples/output_12_0.png
gbeampro-1.0.0.dist-info/METADATA
gbeampro-1.0.0.dist-info/WHEEL
gbeampro-1.0.0.dist-info/licenses/LICENSE
gbeampro-1.0.0.dist-info/RECORD
