Metadata-Version: 2.4
Name: gbeampro
Version: 1.0.0
Summary: Python package for designing gaussian laser beam propagation and transformation. 
Project-URL: Homepage, https://github.com/akihiko-shimura/gbeampro
Author-email: Akihiko Shimura <akhksh@gmail.com>
License: MIT License
License-File: LICENSE
Classifier: License :: OSI Approved :: MIT License
Classifier: Operating System :: OS Independent
Classifier: Programming Language :: Python :: 3
Classifier: Programming Language :: Python :: 3.7
Classifier: Programming Language :: Python :: 3.8
Classifier: Programming Language :: Python :: 3.9
Classifier: Programming Language :: Python :: 3.10
Classifier: Programming Language :: Python :: 3.11
Requires-Dist: numpy
